__init__.py
curvepipe/__init__.py
curvepipe/curve_pipe.py
curvepipe-0.0.2.dist-info/LICENSE
curvepipe-0.0.2.dist-info/METADATA
curvepipe-0.0.2.dist-info/WHEEL
curvepipe-0.0.2.dist-info/top_level.txt
curvepipe-0.0.2.dist-info/RECORD
