Metadata-Version: 2.1
Name: curvepipe
Version: 0.0.2
Summary: Efficient curve-processing package with easily readable syntax
Author-email: Marwin Budniok <marwin.budniok@aol.com>
Project-URL: Homepage, https://github.com/marwin-budniok/curvepipe
Classifier: Programming Language :: Python :: 3
Classifier: License :: OSI Approved :: MIT License
Classifier: Operating System :: OS Independent
Requires-Python: >=3.7
License-File: LICENSE
